commmodelpy/__init__.py
commmodelpy/commmodelpy.py
commmodelpy/submodules/__init__.py
commmodelpy/submodules/helper_general.py
commmodelpy-0.0.3.dist-info/LICENSE
commmodelpy-0.0.3.dist-info/METADATA
commmodelpy-0.0.3.dist-info/WHEEL
commmodelpy-0.0.3.dist-info/top_level.txt
commmodelpy-0.0.3.dist-info/RECORD
