Metadata-Version: 2.1
Name: commmodelpy
Version: 0.0.3
Summary: The commmodelpy package
Home-page: https://github.com/ARB-Lab/commmodelpy
Author: Paulocracy
Author-email: bekiaris@mpi-magdeburg.mpg.de
License: UNKNOWN
Platform: UNKNOWN
Classifier: Programming Language :: Python :: 3
Classifier: License :: OSI Approved :: Apache Software License
Classifier: Operating System :: OS Independent
Requires-Python: >=3.7
Requires-Dist: cobra
